dissec/__init__.py
dissec/errors.py
dissec/keys.py
dissec/patterns.py
dissec/py.typed
dissec/utils.py
dissec-1.1.dist-info/LICENSE.txt
dissec-1.1.dist-info/METADATA
dissec-1.1.dist-info/WHEEL
dissec-1.1.dist-info/RECORD
