Metadata-Version: 2.3
Name: dissec
Version: 1.1
Summary: Dissect pattern implementation for ElasticSearch
Keywords: elasticsearch,dissect,processor,parsing
Author: Thomas Touhey
Author-email: thomas@touhey.fr
Requires-Python: >=3.9,<4.0
Classifier: Development Status :: 5 - Production/Stable
Classifier: Intended Audience :: Developers
Classifier: Intended Audience :: System Administrators
Classifier: License :: CeCILL-C Free Software License Agreement (CECILL-C)
Classifier: Programming Language :: Python :: 3
Classifier: Programming Language :: Python :: 3 :: Only
Classifier: Topic :: Text Processing :: Filters
Classifier: Topic :: Utilities
Classifier: Typing :: Typed
Requires-Dist: eval-type-backport (>=0.2,<0.3) ; python_version < "3.10"
Requires-Dist: pydantic (>=2.7.1,<3)
Requires-Dist: typing-extensions (>=4.12.2,<5)
Project-URL: Bug Tracker, https://gitlab.com/kaquel/dissec/-/issues
Project-URL: Documentation, https://dissec.touhey.pro/
Project-URL: Homepage, https://dissec.touhey.pro/
Project-URL: Source Code, https://gitlab.com/kaquel/dissec
